Metadata-Version: 2.1
Name: libpythonpro01
Version: 0.3
Summary: Modulo para contrução de projetos Python
Home-page: https://github.com/cyaconquista/libpythonpro
Author: Manoel Messias
Author-email: messiasdedeus@hotmail.com
License:                     GNU AFFERO GENERAL PUBLIC LICENSE
Platform: UNKNOWN
Classifier: Development Status :: 2 - Pre-Alpha
Classifier: Environment :: Console
Classifier: Intended Audience :: Developers
Classifier: License :: OSI Approved :: GNU Affero General Public License v3 or later (AGPLv3+)
Classifier: Operating System :: OS Independent
Classifier: Programming Language :: Python
Classifier: Framework :: Pytest
License-File: LICENSE
